nucwf/__init__.py
nucwf/access-w-msig-patch.py
nucwf/access.py
nucwf-1.1.0.dist-info/LICENSE
nucwf-1.1.0.dist-info/METADATA
nucwf-1.1.0.dist-info/WHEEL
nucwf-1.1.0.dist-info/top_level.txt
nucwf-1.1.0.dist-info/RECORD
