Metadata-Version: 2.1
Name: nucwf
Version: 1.1.0
Summary: Package to access nuclear wave functions and Faddeev- or Yakubovsky components for A=3 and 4 nuclei
Author-email: Andreas Nogga <a.nogga@fz-juelich.de>
License: GNU General Public License v3 (GPLv3)
Project-URL: Homepage, https://jugit.fz-juelich.de/a.nogga/nucwavef
Project-URL: Bug Tracker, https://jugit.fz-juelich.de/a.nogga/nucwavef/issues
Classifier: Programming Language :: Python :: 3
Classifier: License :: OSI Approved :: GNU General Public License v3 (GPLv3)
Classifier: Operating System :: OS Independent
Requires-Python: >=3.7
License-File: LICENSE
Requires-Dist: pandas
Requires-Dist: requests
Requires-Dist: numpy
Requires-Dist: h5py
Requires-Dist: hdf5plugin
